setup.py
ToNFToolz/__init__.py
ToNFToolz/funcs.py
ToNFToolz/utils.py
ToNFToolz.egg-info/PKG-INFO
ToNFToolz.egg-info/SOURCES.txt
ToNFToolz.egg-info/dependency_links.txt
ToNFToolz.egg-info/requires.txt
ToNFToolz.egg-info/top_level.txt