Metadata-Version: 2.1
Name: ToNFToolz
Version: 1.3.0
Summary: Explore NFT Items in TON Blockchain
Home-page: 
Author: yungwine
Author-email: cyrbatoff@gmail.com
License: MIT License
